statql/__main__.py
statql/app/__init__.py
statql/app/app.py
statql/app/common.py
statql/app/integrations.py
statql/app/query_console.py
statql/common/__init__.py
statql/common/cache.py
statql/common/definitions.py
statql/common/secrets.py
statql/common/statistics.py
statql/common/utils.py
statql/framework/__init__.py
statql/framework/client/__init__.py
statql/framework/client/client.py
statql/framework/client/plugins_manager.py
statql/framework/client/query_executor.py
statql/framework/client/query_planner.py
statql/framework/client/quey_parser.py
statql/framework/common/__init__.py
statql/framework/common/interface.py
statql/framework/common/terms.py
statql/framework/common/utils.py
statql/framework/logic/__init__.py
statql/framework/logic/aggregate.py
statql/framework/logic/filter.py
statql/framework/logic/limit.py
statql/framework/logic/materialize.py
statql/framework/logic/order.py
statql/framework/logic/project.py
statql/framework/logic/reservoir.py
statql/framework/logic/sample_reservoir.py
statql/framework/logic/scalar_functions.py
statql/framework/logic/scan.py
statql/framework/logic/update_reservoir.py
statql/system_plugins/__init__.py
statql/system_plugins/filesystem/__init__.py
statql/system_plugins/filesystem/connector.py
statql/system_plugins/filesystem/definitions.py
statql/system_plugins/filesystem/fe_controller.py
statql/system_plugins/neo4j/__init__.py
statql/system_plugins/neo4j/client.py
statql/system_plugins/neo4j/connector.py
statql/system_plugins/neo4j/definitions.py
statql/system_plugins/neo4j/fe_controller.py
statql/system_plugins/postgres/__init__.py
statql/system_plugins/postgres/client.py
statql/system_plugins/postgres/connections_manager.py
statql/system_plugins/postgres/connector.py
statql/system_plugins/postgres/definitions.py
statql/system_plugins/postgres/fe_controller.py
statql/system_plugins/postgres/introspector.py
statql/system_plugins/redis/__init__.py
statql/system_plugins/redis/connector.py
statql-0.3.0.dist-info/LICENSE
statql-0.3.0.dist-info/METADATA
statql-0.3.0.dist-info/WHEEL
statql-0.3.0.dist-info/entry_points.txt
statql-0.3.0.dist-info/RECORD
