Metadata-Version: 2.3
Name: statql
Version: 0.3.0
Summary: Approximate, streaming SQL engine
License: Apache-2.0
Author: liel
Author-email: liellahat@gmail.com
Requires-Python: >=3.12,<4.0
Classifier: License :: OSI Approved :: Apache Software License
Classifier: Programming Language :: Python :: 3
Classifier: Programming Language :: Python :: 3.12
Classifier: Programming Language :: Python :: 3.13
Requires-Dist: cryptography (>=44.0.2,<45.0.0)
Requires-Dist: duckdb (>=1.2.2,<2.0.0)
Requires-Dist: keyring (>=25.6.0,<26.0.0)
Requires-Dist: neo4j (>=5.28.1,<6.0.0)
Requires-Dist: pandas (>=2.2.3,<3.0.0)
Requires-Dist: platformdirs (>=4.3.7,<5.0.0)
Requires-Dist: psycopg[binary] (>=3.2.6,<4.0.0)
Requires-Dist: pydantic (>=2.11.3,<3.0.0)
Requires-Dist: redis (>=5.2.1,<6.0.0)
Requires-Dist: sqlglot (>=26.13.0,<27.0.0)
Requires-Dist: streamlit (>=1.44.1,<2.0.0)
Requires-Dist: streamlit-code-editor (>=0.1.22,<0.2.0)
Requires-Dist: testcontainers (>=4.10.0,<5.0.0)
